nicesrt/__init__.py
nicesrt/file_selector.py
nicesrt/geo.py
nicesrt/leaflet.js
nicesrt/leaflet.py
nicesrt/local_filepicker.py
nicesrt/map.py
nicesrt/nicesrt_cmd.py
nicesrt/profiler.py
nicesrt/srt.py
nicesrt/version.py
nicesrt/webserver.py
nicesrt_examples/sample0.SRT
nicesrt_examples/sample1.SRT
nicesrt_examples/sample2.SRT
nicesrt_examples/sample3.SRT
nicesrt_examples/sample4.SRT
nicesrt-0.0.7.dist-info/METADATA
nicesrt-0.0.7.dist-info/WHEEL
nicesrt-0.0.7.dist-info/entry_points.txt
nicesrt-0.0.7.dist-info/licenses/LICENSE
nicesrt-0.0.7.dist-info/RECORD
