Metadata-Version: 2.1
Name: nicesrt
Version: 0.0.7
Project-URL: Home, https://github.com/WolfgangFahl/nicesrt
Project-URL: Documentation, https://wiki.bitplan.com/index.php/nicesrt
Project-URL: Source, https://github.com/WolfgangFahl/nicesrt
Author-email: Wolfgang Fahl <wf@bitplan.com>
Maintainer-email: Wolfgang Fahl <wf@bitplan.com>
License-Expression: Apache-2.0
License-File: LICENSE
Classifier: Development Status :: 4 - Beta
Classifier: Environment :: Web Environment
Classifier: Intended Audience :: Developers
Classifier: Intended Audience :: Education
Classifier: Intended Audience :: Science/Research
Classifier: License :: OSI Approved :: Apache Software License
Classifier: Operating System :: OS Independent
Classifier: Programming Language :: Python :: 3 :: Only
Classifier: Programming Language :: Python :: 3.8
Classifier: Programming Language :: Python :: 3.9
Classifier: Programming Language :: Python :: 3.10
Classifier: Programming Language :: Python :: 3.11
Classifier: Topic :: Software Development :: Libraries :: Python Modules
Requires-Python: >=3.8
Requires-Dist: nicegui>=1.3.9
Requires-Dist: osmpythontools
Requires-Dist: pysrt
Provides-Extra: test
Requires-Dist: green; extra == 'test'
